wagtail_icons/__init__.py
wagtail_icons/base.py
wagtail_icons/settings.py
wagtail_icons/wagtail_hooks.py
wagtail_icons/contrib/__init__.py
wagtail_icons/contrib/fontawesome.py
wagtail_icons/contrib/icomoon.py
wagtail_icons/static/wagtail_icons/contrib/fontawesome-free-5.15.4-web/LICENSE.txt
wagtail_icons/static/wagtail_icons/contrib/fontawesome-free-5.15.4-web/css/all.css
wagtail_icons/static/wagtail_icons/contrib/fontawesome-free-5.15.4-web/css/all.min.css
wagtail_icons/static/wagtail_icons/contrib/fontawesome-free-5.15.4-web/css/brands.css
wagtail_icons/static/wagtail_icons/contrib/fontawesome-free-5.15.4-web/css/brands.min.css
wagtail_icons/static/wagtail_icons/contrib/fontawesome-free-5.15.4-web/css/fontawesome.css
wagtail_icons/static/wagtail_icons/contrib/fontawesome-free-5.15.4-web/css/fontawesome.min.css
wagtail_icons/static/wagtail_icons/contrib/fontawesome-free-5.15.4-web/css/regular.css
wagtail_icons/static/wagtail_icons/contrib/fontawesome-free-5.15.4-web/css/regular.min.css
wagtail_icons/static/wagtail_icons/contrib/fontawesome-free-5.15.4-web/css/solid.css
wagtail_icons/static/wagtail_icons/contrib/fontawesome-free-5.15.4-web/css/solid.min.css
wagtail_icons/static/wagtail_icons/contrib/fontawesome-free-5.15.4-web/css/svg-with-js.css
wagtail_icons/static/wagtail_icons/contrib/fontawesome-free-5.15.4-web/css/svg-with-js.min.css
wagtail_icons/static/wagtail_icons/contrib/fontawesome-free-5.15.4-web/css/v4-shims.css
wagtail_icons/static/wagtail_icons/contrib/fontawesome-free-5.15.4-web/css/v4-shims.min.css
wagtail_icons/static/wagtail_icons/contrib/fontawesome-free-5.15.4-web/webfonts/fa-brands-400.eot
wagtail_icons/static/wagtail_icons/contrib/fontawesome-free-5.15.4-web/webfonts/fa-brands-400.svg
wagtail_icons/static/wagtail_icons/contrib/fontawesome-free-5.15.4-web/webfonts/fa-brands-400.ttf
wagtail_icons/static/wagtail_icons/contrib/fontawesome-free-5.15.4-web/webfonts/fa-brands-400.woff
wagtail_icons-0.1.0.dist-info/LICENSE
wagtail_icons-0.1.0.dist-info/METADATA
wagtail_icons-0.1.0.dist-info/WHEEL
wagtail_icons-0.1.0.dist-info/top_level.txt
wagtail_icons-0.1.0.dist-info/RECORD
