Metadata-Version: 2.1
Name: wagtail-icons
Version: 0.1.0
Summary: UNKNOWN
Home-page: UNKNOWN
Author: R. Moorman <rob@vicktor.nl>
License: UNKNOWN
Platform: UNKNOWN
Classifier: Environment :: Web Environment
Classifier: Framework :: Django
Classifier: Operating System :: Unix
Classifier: Programming Language :: Python :: 3
Requires-Dist: django (>=3)
Requires-Dist: wagtail (>=2)
Provides-Extra: test
Requires-Dist: black ; extra == 'test'
Requires-Dist: flake8 ; extra == 'test'
Requires-Dist: isort ; extra == 'test'
Requires-Dist: pytest ; extra == 'test'
Requires-Dist: pytest-django ; extra == 'test'
